<?xml version="1.0" encoding="UTF-8"?>
<osm version="0.6" generator="CGImap 0.6.0 (9706 thorn-01.openstreetmap.org)" copyright="OpenStreetMap and contributors" attribution="http://www.openstreetmap.org/copyright" license="http://opendatacommons.org/licenses/odbl/1-0/">
 <node id="256016208" visible="true" version="9" changeset="49017271" timestamp="2017-05-27T06:09:15Z" user="SHCat" uid="4641415" lat="22.9920242" lon="120.2216173"/>
 <node id="256016221" visible="true" version="14" changeset="57282747" timestamp="2018-03-18T06:33:23Z" user="SHCat" uid="4641415" lat="22.9923454" lon="120.2178628"/>
 <node id="256016226" visible="true" version="16" changeset="57282747" timestamp="2018-03-18T06:33:23Z" user="SHCat" uid="4641415" lat="23.0008856" lon="120.2185401">
  <tag k="highway" v="traffic_signals"/>
 </node>
 <node id="296967567" visible="true" version="9" changeset="51772102" timestamp="2017-09-06T07:43:47Z" user="SHCat" uid="4641415" lat="22.9884792" lon="120.2335109">
  <tag k="highway" v="traffic_signals"/>
 </node>
 <node id="335913528" visible="true" version="9" changeset="42614801" timestamp="2016-10-03T20:28:10Z" user="Luis36995" uid="1829683" lat="22.9884823" lon="120.2336012">
  <tag k="highway" v="traffic_signals"/>
 </node>
 <node id="355961064" visible="true" version="15" changeset="57282747" timestamp="2018-03-18T06:33:23Z" user="SHCat" uid="4641415" lat="22.9962363" lon="120.2181644"/>
 <node id="864831599" visible="true" version="10" changeset="57058773" timestamp="2018-03-10T13:59:05Z" user="SHCat" uid="4641415" lat="22.9976030" lon="120.2122751">
  <tag k="highway" v="traffic_signals"/>
 </node>
 <node id="1240617667" visible="true" version="7" changeset="56522849" timestamp="2018-02-20T14:46:43Z" user="SHCat" uid="4641415" lat="23.0015329" lon="120.2145258">
  <tag k="highway" v="crossing"/>
 </node>
 <node id="1240617783" visible="true" version="4" changeset="56522849" timestamp="2018-02-20T14:46:43Z" user="SHCat" uid="4641415" lat="23.0016633" lon="120.2132007"/>
 <node id="1240618031" visible="true" version="9" changeset="56512917" timestamp="2018-02-20T08:02:34Z" user="SHCat" uid="4641415" lat="23.0016447" lon="120.2130526">
  <tag k="highway" v="traffic_signals"/>
 </node>
 <node id="1240618115" visible="true" version="8" changeset="56663456" timestamp="2018-02-25T15:19:12Z" user="SHCat" uid="4641415" lat="22.9867927" lon="120.2290501"/>
 <node id="1240618141" visible="true" version="7" changeset="53440308" timestamp="2017-11-02T04:29:27Z" user="SHCat" uid="4641415" lat="22.9854655" lon="120.2225335"/>
 <node id="1240618154" visible="true" version="3" changeset="24767017" timestamp="2014-08-15T13:16:41Z" user="Kagami" uid="189328" lat="23.0016817" lon="120.2130937"/>
 <node id="1240618163" visible="true" version="7" changeset="53440308" timestamp="2017-11-02T04:29:27Z" user="SHCat" uid="4641415" lat="22.9911408" lon="120.2244100">
  <tag k="highway" v="traffic_signals"/>
 </node>
 <node id="1240618188" visible="true" version="9" changeset="42381354" timestamp="2016-09-23T17:24:31Z" user="Luis36995" uid="1829683" lat="22.9999659" lon="120.2127411">
  <tag k="highway" v="traffic_signals"/>
 </node>
 <node id="1240618278" visible="true" version="8" changeset="57282747" timestamp="2018-03-18T06:33:22Z" user="SHCat" uid="4641415" lat="23.0010478" lon="120.2185555">
  <tag k="highway" v="traffic_signals"/>
 </node>
 <node id="1240618302" visible="true" version="7" changeset="49017629" timestamp="2017-05-27T06:42:03Z" user="SHCat" uid="4641415" lat="22.9848414" lon="120.2243291"/>
 <node id="1240618340" visible="true" version="9" changeset="56512917" timestamp="2018-02-20T08:02:34Z" user="SHCat" uid="4641415" lat="23.0015091" lon="120.2146578">
  <tag k="highway" v="traffic_signals"/>
 </node>
 <node id="1240618440" visible="true" version="5" changeset="53440308" timestamp="2017-11-02T04:29:27Z" user="SHCat" uid="4641415" lat="22.9910887" lon="120.2245770">
  <tag k="highway" v="traffic_signals"/>
 </node>
 <node id="1240618461" visible="true" version="4" changeset="50112791" timestamp="2017-07-07T16:16:07Z" user="SHCat" uid="4641415" lat="23.0014801" lon="120.2143721"/>
 <node id="1240618561" visible="true" version="7" changeset="56663456" timestamp="2018-02-25T15:19:12Z" user="SHCat" uid="4641415" lat="22.9858434" lon="120.2269056"/>
 <node id="1240618649" visible="true" version="8" changeset="42381354" timestamp="2016-09-23T17:24:31Z" user="Luis36995" uid="1829683" lat="23.0016892" lon="120.2130610">
  <tag k="highway" v="traffic_signals"/>
 </node>
 <node id="1268711590" visible="true" version="10" changeset="57282747" timestamp="2018-03-18T06:33:23Z" user="SHCat" uid="4641415" lat="22.9953759" lon="120.2180960"/>
 <node id="1268711606" visible="true" version="7" changeset="57058773" timestamp="2018-03-10T13:59:04Z" user="SHCat" uid="4641415" lat="22.9985075" lon="120.2124535">
  <tag k="highway" v="traffic_signals"/>
 </node>
 <node id="1268711613" visible="true" version="6" changeset="42381354" timestamp="2016-09-23T17:24:31Z" user="Luis36995" uid="1829683" lat="23.0000177" lon="120.2127492"/>
 <node id="1650294487" visible="true" version="7" changeset="49017271" timestamp="2017-05-27T06:09:15Z" user="SHCat" uid="4641415" lat="22.9920653" lon="120.2215513"/>
 <node id="1650311027" visible="true" version="9" changeset="56663456" timestamp="2018-02-25T15:19:12Z" user="SHCat" uid="4641415" lat="22.9855627" lon="120.2261837"/>
 <node id="1650311040" visible="true" version="4" changeset="53440308" timestamp="2017-11-02T04:29:27Z" user="SHCat" uid="4641415" lat="22.9871358" lon="120.2230734"/>
 <node id="1650311059" visible="true" version="6" changeset="56523599" timestamp="2018-02-20T15:17:31Z" user="SHCat" uid="4641415" lat="22.9878121" lon="120.2233323"/>
 <node id="1721697101" visible="true" version="8" changeset="42615772" timestamp="2016-10-03T21:19:37Z" user="Luis36995" uid="1829683" lat="22.9852544" lon="120.2231739"/>
 <node id="1721697102" visible="true" version="6" changeset="56527369" timestamp="2018-02-20T17:28:45Z" user="SHCat" uid="4641415" lat="22.9853986" lon="120.2227375"/>
 <node id="1721697108" visible="true" version="10" changeset="56663456" timestamp="2018-02-25T15:19:12Z" user="SHCat" uid="4641415" lat="22.9885074" lon="120.2328848">
  <tag k="highway" v="traffic_signals"/>
 </node>
 <node id="1721697109" visible="true" version="7" changeset="51772102" timestamp="2017-09-06T07:43:47Z" user="SHCat" uid="4641415" lat="22.9884660" lon="120.2331423">
  <tag k="highway" v="traffic_signals"/>
 </node>
 <node id="1723131384" visible="true" version="10" changeset="56663456" timestamp="2018-02-25T15:19:12Z" user="SHCat" uid="4641415" lat="22.9869883" lon="120.2294874"/>
 <node id="1723131385" visible="true" version="9" changeset="56663456" timestamp="2018-02-25T15:19:12Z" user="SHCat" uid="4641415" lat="22.9870231" lon="120.2295653"/>
 <node id="1723131428" visible="true" version="7" changeset="53440308" timestamp="2017-11-02T04:29:27Z" user="SHCat" uid="4641415" lat="22.9891990" lon="120.2238582">
  <tag k="highway" v="traffic_signals"/>
 </node>
 <node id="1723131486" visible="true" version="8" changeset="56567816" timestamp="2018-02-22T03:52:15Z" user="SHCat" uid="4641415" lat="22.9917520" lon="120.2224265"/>
 <node id="1723131492" visible="true" version="5" changeset="51772102" timestamp="2017-09-06T07:43:47Z" user="SHCat" uid="4641415" lat="22.9922564" lon="120.2192132"/>
 <node id="1723635440" visible="true" version="6" changeset="53440308" timestamp="2017-11-02T04:29:27Z" user="SHCat" uid="4641415" lat="22.9888072" lon="120.2237092"/>
 <node id="1723635450" visible="true" version="4" changeset="49017271" timestamp="2017-05-27T06:09:15Z" user="SHCat" uid="4641415" lat="22.9913926" lon="120.2236123"/>
 <node id="1723635452" visible="true" version="6" changeset="53440308" timestamp="2017-11-02T04:29:26Z" user="SHCat" uid="4641415" lat="22.9916488" lon="120.2227943"/>
 <node id="1723635528" visible="true" version="9" changeset="57282747" timestamp="2018-03-18T06:33:23Z" user="SHCat" uid="4641415" lat="22.9955942" lon="120.2181146"/>
 <node id="1723635535" visible="true" version="9" changeset="57282747" timestamp="2018-03-18T06:33:23Z" user="SHCat" uid="4641415" lat="22.9957368" lon="120.2181257"/>
 <node id="1723635546" visible="true" version="9" changeset="57282747" timestamp="2018-03-18T06:33:23Z" user="SHCat" uid="4641415" lat="22.9958830" lon="120.2181370"/>
 <node id="1723635551" visible="true" version="9" changeset="57282747" timestamp="2018-03-18T06:33:23Z" user="SHCat" uid="4641415" lat="22.9960205" lon="120.2181476"/>
 <node id="1725808263" visible="true" version="6" changeset="51949335" timestamp="2017-09-11T17:37:55Z" user="Kagami" uid="189328" lat="22.9793442" lon="120.2418151"/>
 <node id="1725808298" visible="true" version="5" changeset="50235794" timestamp="2017-07-12T17:05:20Z" user="SHCat" uid="4641415" lat="22.9798789" lon="120.2450451"/>
 <node id="1725808300" visible="true" version="7" changeset="50235794" timestamp="2017-07-12T17:05:20Z" user="SHCat" uid="4641415" lat="22.9798749" lon="120.2444866"/>
 <node id="1725808301" visible="true" version="7" changeset="50235794" timestamp="2017-07-12T17:05:20Z" user="SHCat" uid="4641415" lat="22.9798671" lon="120.2434904"/>
 <node id="1725808303" visible="true" version="7" changeset="50235794" timestamp="2017-07-12T17:05:20Z" user="SHCat" uid="4641415" lat="22.9798555" lon="120.2418336"/>
 <node id="1725808398" visible="true" version="7" changeset="49028461" timestamp="2017-05-27T16:24:21Z" user="SHCat" uid="4641415" lat="22.9822970" lon="120.2434959"/>
 <node id="1725808411" visible="true" version="6" changeset="49028461" timestamp="2017-05-27T16:24:21Z" user="SHCat" uid="4641415" lat="22.9823058" lon="120.2450764"/>
 <node id="1725808418" visible="true" version="3" changeset="18006261" timestamp="2013-09-24T10:21:16Z" user="wenchin" uid="121778" lat="22.9826530" lon="120.2417744"/>
 <node id="1725808448" visible="true" version="5" changeset="50235794" timestamp="2017-07-12T17:05:19Z" user="SHCat" uid="4641415" lat="22.9834037" lon="120.2417813"/>
 <node id="1725808505" visible="true" version="7" changeset="50235794" timestamp="2017-07-12T17:05:19Z" user="SHCat" uid="4641415" lat="22.9849582" lon="120.2417956"/>
 <node id="1725808538" visible="true" version="6" changeset="49008145" timestamp="2017-05-26T17:28:50Z" user="SHCat" uid="4641415" lat="22.9850532" lon="120.2416875"/>
 <node id="1725808539" visible="true" version="4" changeset="42521204" timestamp="2016-09-29T14:50:21Z" user="piligab" uid="3877019" lat="22.9850574" lon="120.2417965"/>
 <node id="1725808540" visible="true" version="6" changeset="50235794" timestamp="2017-07-12T17:05:19Z" user="SHCat" uid="4641415" lat="22.9850601" lon="120.2411399"/>
 <node id="1725808562" visible="true" version="4" changeset="42521204" timestamp="2016-09-29T14:50:21Z" user="piligab" uid="3877019" lat="22.9850720" lon="120.2396082"/>
 <node id="1725808608" visible="true" version="6" changeset="50235794" timestamp="2017-07-12T17:05:22Z" user="SHCat" uid="4641415" lat="22.9856567" lon="120.2396153"/>
 <node id="1725808648" visible="true" version="6" changeset="50235794" timestamp="2017-07-12T17:05:22Z" user="SHCat" uid="4641415" lat="22.9867256" lon="120.2396283"/>
 <node id="1725808713" visible="true" version="6" changeset="50235794" timestamp="2017-07-12T17:05:23Z" user="SHCat" uid="4641415" lat="22.9876068" lon="120.2395800"/>
 <node id="1725808751" visible="true" version="6" changeset="50235794" timestamp="2017-07-12T17:05:23Z" user="SHCat" uid="4641415" lat="22.9885552" lon="120.2394602"/>
 <node id="1725808770" visible="true" version="4" changeset="42464560" timestamp="2016-09-27T08:51:28Z" user="saikabhi" uid="3029661" lat="22.9888311" lon="120.2382343"/>
 <node id="1725808772" visible="true" version="6" changeset="50235794" timestamp="2017-07-12T17:05:23Z" user="SHCat" uid="4641415" lat="22.9889235" lon="120.2387886"/>
 <node id="1727568976" visible="true" version="7" changeset="56663456" timestamp="2018-02-25T15:19:12Z" user="SHCat" uid="4641415" lat="22.9849324" lon="120.2245630"/>
 <node id="1727568978" visible="true" version="5" changeset="42520099" timestamp="2016-09-29T14:21:36Z" user="piligab" uid="3877019" lat="22.9851032" lon="120.2236310"/>
 <node id="1727569026" visible="true" version="4" changeset="53440308" timestamp="2017-11-02T04:29:27Z" user="SHCat" uid="4641415" lat="22.9864932" lon="120.2228657"/>
 <node id="1727569033" visible="true" version="7" changeset="56663456" timestamp="2018-02-25T15:19:12Z" user="SHCat" uid="4641415" lat="22.9865228" lon="120.2284466"/>
 <node id="1728838658" visible="true" version="8" changeset="56663456" timestamp="2018-02-25T15:19:12Z" user="SHCat" uid="4641415" lat="22.9876117" lon="120.2308817"/>
 <node id="1728838681" visible="true" version="7" changeset="56663456" timestamp="2018-02-25T15:19:12Z" user="SHCat" uid="4641415" lat="22.9880030" lon="120.2317567"/>
 <node id="2144927860" visible="true" version="4" changeset="57058773" timestamp="2018-03-10T13:59:05Z" user="SHCat" uid="4641415" lat="22.9995165" lon="120.2126525"/>
 <node id="2144927867" visible="true" version="4" changeset="57058773" timestamp="2018-03-10T13:59:05Z" user="SHCat" uid="4641415" lat="22.9997975" lon="120.2127079"/>
 <node id="2163590079" visible="true" version="8" changeset="28581750" timestamp="2015-02-03T04:54:47Z" user="Supaplex" uid="274857" lat="23.0005175" lon="120.2126986">
  <tag k="bench" v="yes"/>
  <tag k="bus" v="yes"/>
  <tag k="highway" v="bus_stop"/>
  <tag k="name" v="台南公園(北門路)"/>
  <tag k="network" v="臺南市公車"/>
  <tag k="operator" v="臺南市公車"/>
  <tag k="public_transport" v="platform"/>
  <tag k="shelter" v="yes"/>
 </node>
 <node id="2163590085" visible="true" version="7" changeset="28581750" timestamp="2015-02-03T04:55:42Z" user="Supaplex" uid="274857" lat="23.0013823" lon="120.2158057">
  <tag k="bus" v="yes"/>
  <tag k="highway" v="bus_stop"/>
  <tag k="name" v="小東路"/>
  <tag k="network" v="臺南市公車"/>
  <tag k="operator" v="臺南市公車"/>
  <tag k="public_transport" v="platform"/>
 </node>
 <node id="2163590091" visible="true" version="8" changeset="28581750" timestamp="2015-02-03T04:56:06Z" user="Supaplex" uid="274857" lat="23.0011082" lon="120.2181700">
  <tag k="bus" v="yes"/>
  <tag k="highway" v="bus_stop"/>
  <tag k="name" v="成功大學"/>
  <tag k="network" v="臺南市公車"/>
  <tag k="operator" v="臺南市公車"/>
  <tag k="public_transport" v="platform"/>
 </node>
 <node id="2204802270" visible="true" version="8" changeset="56663456" timestamp="2018-02-25T15:19:12Z" user="SHCat" uid="4641415" lat="22.9870929" lon="120.2297214"/>
 <node id="2204802343" visible="true" version="6" changeset="42614458" timestamp="2016-10-03T20:10:47Z" user="Luis36995" uid="1829683" lat="22.9884831" lon="120.2339734">
  <tag k="highway" v="traffic_signals"/>
 </node>
 <node id="2204802349" visible="true" version="5" changeset="42521204" timestamp="2016-09-29T14:50:21Z" user="piligab" uid="3877019" lat="22.9885499" lon="120.2355546"/>
 <node id="2205385002" visible="true" version="3" changeset="24836872" timestamp="2014-08-18T15:59:42Z" user="Kagami" uid="189328" lat="22.9850631" lon="120.2402403"/>
 <node id="2205385018" visible="true" version="8" changeset="56663456" timestamp="2018-02-25T15:19:12Z" user="SHCat" uid="4641415" lat="22.9859857" lon="120.2272454"/>
 <node id="2205385043" visible="true" version="5" changeset="50235794" timestamp="2017-07-12T17:05:22Z" user="SHCat" uid="4641415" lat="22.9871806" lon="120.2396339"/>
 <node id="2205385055" visible="true" version="5" changeset="50235794" timestamp="2017-07-12T17:05:23Z" user="SHCat" uid="4641415" lat="22.9881832" lon="120.2395072"/>
 <node id="2205385078" visible="true" version="4" changeset="42464560" timestamp="2016-09-27T08:51:28Z" user="saikabhi" uid="3029661" lat="22.9886286" lon="120.2365138"/>
 <node id="2239492102" visible="true" version="7" changeset="42521204" timestamp="2016-09-29T14:50:22Z" user="piligab" uid="3877019" lat="22.9885737" lon="120.2356278"/>
 <node id="2467264692" visible="true" version="6" changeset="51772102" timestamp="2017-09-06T07:43:47Z" user="SHCat" uid="4641415" lat="22.9921683" lon="120.2202909"/>
 <node id="2469869715" visible="true" version="4" changeset="50235794" timestamp="2017-07-12T17:05:20Z" user="SHCat" uid="4641415" lat="22.9798771" lon="120.2451621"/>
 <node id="2469869717" visible="true" version="4" changeset="50235794" timestamp="2017-07-12T17:05:20Z" user="SHCat" uid="4641415" lat="22.9798579" lon="120.2420694"/>
 <node id="2469869719" visible="true" version="4" changeset="50235794" timestamp="2017-07-12T17:05:20Z" user="SHCat" uid="4641415" lat="22.9798594" lon="120.2423398"/>
 <node id="2469869721" visible="true" version="4" changeset="50235794" timestamp="2017-07-12T17:05:20Z" user="SHCat" uid="4641415" lat="22.9798610" lon="120.2426163"/>
 <node id="2469869722" visible="true" version="4" changeset="50235794" timestamp="2017-07-12T17:05:20Z" user="SHCat" uid="4641415" lat="22.9798631" lon="120.2429743"/>
 <node id="2469869745" visible="true" version="7" changeset="50235794" timestamp="2017-07-12T17:05:21Z" user="SHCat" uid="4641415" lat="22.9804107" lon="120.2451683"/>
 <node id="2469869754" visible="true" version="8" changeset="50235794" timestamp="2017-07-12T17:05:21Z" user="SHCat" uid="4641415" lat="22.9806054" lon="120.2451715"/>
 <node id="2469869835" visible="true" version="6" changeset="50235794" timestamp="2017-07-12T17:05:21Z" user="SHCat" uid="4641415" lat="22.9818203" lon="120.2451862"/>
 <node id="2469869860" visible="true" version="5" changeset="49028461" timestamp="2017-05-27T16:24:21Z" user="SHCat" uid="4641415" lat="22.9823064" lon="120.2451915"/>
 <node id="2469869909" visible="true" version="4" changeset="50235794" timestamp="2017-07-12T17:05:19Z" user="SHCat" uid="4641415" lat="22.9837421" lon="120.2417844"/>
 <node id="2469869929" visible="true" version="4" changeset="50235794" timestamp="2017-07-12T17:05:19Z" user="SHCat" uid="4641415" lat="22.9840072" lon="120.2417868"/>
 <node id="2578269068" visible="true" version="6" changeset="57282747" timestamp="2018-03-18T06:33:23Z" user="SHCat" uid="4641415" lat="22.9970895" lon="120.2182333"/>
 <node id="2578269075" visible="true" version="5" changeset="57282747" timestamp="2018-03-18T06:33:23Z" user="SHCat" uid="4641415" lat="22.9984422" lon="120.2183426"/>
 <node id="2592689570" visible="true" version="4" changeset="28581750" timestamp="2015-02-03T04:54:26Z" user="Supaplex" uid="274857" lat="22.9980806" lon="120.2183207">
  <tag k="bus" v="yes"/>
  <tag k="highway" v="bus_stop"/>
  <tag k="name" v="勝利路"/>
  <tag k="network" v="臺南市公車"/>
  <tag k="operator" v="臺南市公車"/>
  <tag k="public_transport" v="platform"/>
 </node>
 <node id="2592689573" visible="true" version="4" changeset="28581750" timestamp="2015-02-03T04:54:47Z" user="Supaplex" uid="274857" lat="22.9929330" lon="120.2179269">
  <tag k="bus" v="yes"/>
  <tag k="highway" v="bus_stop"/>
  <tag k="name" v="台南一中"/>
  <tag k="network" v="臺南市公車"/>
  <tag k="operator" v="臺南市公車"/>
  <tag k="public_transport" v="platform"/>
 </node>
 <node id="2592689575" visible="true" version="5" changeset="49669825" timestamp="2017-06-19T15:04:46Z" user="s88239" uid="5406836" lat="22.9958978" lon="120.2181489">
  <tag k="bus" v="yes"/>
  <tag k="highway" v="bus_stop"/>
  <tag k="name" v="成大會館"/>
  <tag k="network" v="臺南市公車"/>
  <tag k="operator" v="臺南市公車"/>
  <tag k="public_transport" v="platform"/>
  <tag k="ref" v="0656"/>
  <tag k="shelter" v="no"/>
 </node>
 <node id="2592689579" visible="true" version="5" changeset="28581750" timestamp="2015-02-03T04:56:07Z" user="Supaplex" uid="274857" lat="22.9922641" lon="120.2197553">
  <tag k="bus" v="yes"/>
  <tag k="highway" v="bus_stop"/>
  <tag k="name" v="成功新村"/>
  <tag k="network" v="臺南市公車"/>
  <tag k="operator" v="臺南市公車"/>
  <tag k="public_transport" v="platform"/>
 </node>
 <node id="2794611790" visible="true" version="7" changeset="50235794" timestamp="2017-07-12T17:05:23Z" user="SHCat" uid="4641415" lat="22.9889588" lon="120.2389949"/>
 <node id="2794611809" visible="true" version="4" changeset="28581750" timestamp="2015-02-03T04:55:25Z" user="Supaplex" uid="274857" lat="22.9862112" lon="120.2275482">
  <tag k="bus" v="yes"/>
  <tag k="highway" v="bus_stop"/>
  <tag k="name" v="妙善寺"/>
  <tag k="network" v="臺南市公車"/>
  <tag k="operator" v="臺南市公車"/>
  <tag k="public_transport" v="platform"/>
 </node>
 <node id="2794611829" visible="true" version="4" changeset="28581750" timestamp="2015-02-03T04:55:47Z" user="Supaplex" uid="274857" lat="22.9894979" lon="120.2239710">
  <tag k="bus" v="yes"/>
  <tag k="highway" v="bus_stop"/>
  <tag k="name" v="崇誨新村"/>
  <tag k="network" v="臺南市公車"/>
  <tag k="operator" v="臺南市公車"/>
  <tag k="public_transport" v="platform"/>
 </node>
 <node id="2794611833" visible="true" version="5" changeset="28581750" timestamp="2015-02-03T04:56:01Z" user="Supaplex" uid="274857" lat="22.9886965" lon="120.2360598">
  <tag k="bus" v="yes"/>
  <tag k="highway" v="bus_stop"/>
  <tag k="name" v="後甲"/>
  <tag k="network" v="臺南市公車"/>
  <tag k="operator" v="臺南市公車"/>
  <tag k="public_transport" v="platform"/>
 </node>
 <node id="2794611836" visible="true" version="5" changeset="44684838" timestamp="2016-12-26T15:33:37Z" user="Kagami" uid="189328" lat="22.9883068" lon="120.2322189">
  <tag k="bus" v="yes"/>
  <tag k="highway" v="bus_stop"/>
  <tag k="name" v="南紡購物中心(裕農路)"/>
  <tag k="network" v="臺南市公車"/>
  <tag k="operator" v="臺南市公車"/>
  <tag k="public_transport" v="platform"/>
 </node>
 <node id="2794611845" visible="true" version="10" changeset="44518816" timestamp="2016-12-19T15:42:41Z" user="Supaplex" uid="274857" lat="22.9890802" lon="120.2392477">
  <tag k="bus" v="yes"/>
  <tag k="highway" v="bus_stop"/>
  <tag k="name" v="慈幼工商"/>
  <tag k="network" v="臺南市公車"/>
  <tag k="operator" v="臺南市公車"/>
  <tag k="public_transport" v="platform"/>
 </node>
 <node id="2794611858" visible="true" version="4" changeset="28581750" timestamp="2015-02-03T04:56:32Z" user="Supaplex" uid="274857" lat="22.9866786" lon="120.2229337">
  <tag k="bus" v="yes"/>
  <tag k="highway" v="bus_stop"/>
  <tag k="name" v="東門國宅"/>
  <tag k="network" v="臺南市公車"/>
  <tag k="operator" v="臺南市公車"/>
  <tag k="public_transport" v="platform"/>
 </node>
 <node id="2794611872" visible="true" version="4" changeset="28581750" timestamp="2015-02-03T04:57:15Z" user="Supaplex" uid="274857" lat="22.9874986" lon="120.2303930">
  <tag k="bus" v="yes"/>
  <tag k="highway" v="bus_stop"/>
  <tag k="name" v="盛大市場"/>
  <tag k="network" v="臺南市公車"/>
  <tag k="operator" v="臺南市公車"/>
  <tag k="public_transport" v="platform"/>
 </node>
 <node id="2794611893" visible="true" version="4" changeset="28581750" timestamp="2015-02-03T04:57:45Z" user="Supaplex" uid="274857" lat="22.9853556" lon="120.2231763">
  <tag k="bus" v="yes"/>
  <tag k="highway" v="bus_stop"/>
  <tag k="name" v="衛生局"/>
  <tag k="network" v="臺南市公車"/>
  <tag k="operator" v="臺南市公車"/>
  <tag k="public_transport" v="platform"/>
 </node>
 <node id="2794611897" visible="true" version="4" changeset="28581750" timestamp="2015-02-03T04:57:46Z" user="Supaplex" uid="274857" lat="22.9855351" lon="120.2259134">
  <tag k="bus" v="yes"/>
  <tag k="highway" v="bus_stop"/>
  <tag k="name" v="裕農路"/>
  <tag k="network" v="臺南市公車"/>
  <tag k="operator" v="臺南市公車"/>
  <tag k="public_transport" v="platform"/>
 </node>
 <node id="2833118029" visible="true" version="4" changeset="51772102" timestamp="2017-09-06T07:43:47Z" user="SHCat" uid="4641415" lat="22.9921498" lon="120.2205173"/>
 <node id="2833118044" visible="true" version="3" changeset="57058773" timestamp="2018-03-10T13:59:05Z" user="SHCat" uid="4641415" lat="22.9992550" lon="120.2126009"/>
 <node id="2833129211" visible="true" version="4" changeset="51772102" timestamp="2017-09-06T07:43:47Z" user="SHCat" uid="4641415" lat="22.9922433" lon="120.2193732"/>
 <node id="2833144824" visible="true" version="4" changeset="57058773" timestamp="2018-03-10T13:59:05Z" user="SHCat" uid="4641415" lat="22.9982391" lon="120.2124005"/>
 <node id="3019036790" visible="true" version="3" changeset="51772102" timestamp="2017-09-06T07:43:47Z" user="SHCat" uid="4641415" lat="22.9920990" lon="120.2211389"/>
 <node id="3024807439" visible="true" version="3" changeset="28581750" timestamp="2015-02-03T04:56:29Z" user="Supaplex" uid="274857" lat="22.9916048" lon="120.2229915">
  <tag k="bench" v="yes"/>
  <tag k="bus" v="yes"/>
  <tag k="highway" v="bus_stop"/>
  <tag k="name" v="東寧社區"/>
  <tag k="network" v="臺南市公車"/>
  <tag k="operator" v="臺南市公車"/>
  <tag k="public_transport" v="platform"/>
  <tag k="shelter" v="yes"/>
 </node>
 <node id="3024869186" visible="true" version="7" changeset="50235794" timestamp="2017-07-12T17:05:21Z" user="SHCat" uid="4641415" lat="22.9809561" lon="120.2451757"/>
 <node id="3024869198" visible="true" version="3" changeset="28581750" timestamp="2015-02-03T04:57:43Z" user="Supaplex" uid="274857" lat="22.9829174" lon="120.2418269">
  <tag k="bus" v="yes"/>
  <tag k="highway" v="bus_stop"/>
  <tag k="name" v="虎尾寮重劃區"/>
  <tag k="network" v="臺南市公車"/>
  <tag k="operator" v="臺南市公車"/>
  <tag k="public_transport" v="platform"/>
 </node>
 <node id="3024869202" visible="true" version="3" changeset="28581750" timestamp="2015-02-03T04:57:45Z" user="Supaplex" uid="274857" lat="22.9851011" lon="120.2408180">
  <tag k="bus" v="yes"/>
  <tag k="highway" v="bus_stop"/>
  <tag k="name" v="裕平路"/>
  <tag k="network" v="臺南市公車"/>
  <tag k="operator" v="臺南市公車"/>
  <tag k="public_transport" v="platform"/>
 </node>
 <node id="3024869204" visible="true" version="4" changeset="42521204" timestamp="2016-09-29T14:50:20Z" user="piligab" uid="3877019" lat="22.9816467" lon="120.2452299">
  <tag k="bus" v="yes"/>
  <tag k="highway" v="bus_stop"/>
  <tag k="name" v="裕聖公園"/>
  <tag k="network" v="臺南市公車"/>
  <tag k="operator" v="臺南市公車"/>
  <tag k="public_transport" v="platform"/>
 </node>
 <node id="3024869207" visible="true" version="4" changeset="43825666" timestamp="2016-11-20T16:30:17Z" user="Supaplex" uid="274857" lat="22.9878659" lon="120.2395812">
  <tag k="bus" v="yes"/>
  <tag k="highway" v="bus_stop"/>
  <tag k="name" v="裕誠街口"/>
  <tag k="network" v="臺南市公車"/>
  <tag k="operator" v="臺南市公車"/>
  <tag k="public_transport" v="platform"/>
 </node>
 <node id="3024869209" visible="true" version="3" changeset="28581750" timestamp="2015-02-03T04:57:46Z" user="Supaplex" uid="274857" lat="22.9858243" lon="120.2396195">
  <tag k="bus" v="yes"/>
  <tag k="highway" v="bus_stop"/>
  <tag k="name" v="裕農三街"/>
  <tag k="network" v="臺南市公車"/>
  <tag k="operator" v="臺南市公車"/>
  <tag k="public_transport" v="platform"/>
 </node>
 <node id="3070820668" visible="true" version="4" changeset="50235794" timestamp="2017-07-12T17:05:23Z" user="SHCat" uid="4641415" lat="22.9890243" lon="120.2394009"/>
 <node id="3076706423" visible="true" version="3" changeset="51772102" timestamp="2017-09-06T07:43:47Z" user="SHCat" uid="4641415" lat="22.9922373" lon="120.2194470"/>
 <node id="3232607263" visible="true" version="3" changeset="42517779" timestamp="2016-09-29T12:37:31Z" user="upendrakarukonda" uid="4007051" lat="22.9887034" lon="120.2372660"/>
 <node id="3232727826" visible="true" version="4" changeset="42521204" timestamp="2016-09-29T14:50:25Z" user="piligab" uid="3877019" lat="22.9885232" lon="120.2346991"/>
 <node id="3232727827" visible="true" version="3" changeset="42521204" timestamp="2016-09-29T14:50:25Z" user="piligab" uid="3877019" lat="22.9885485" lon="120.2350469"/>
 <node id="3256639839" visible="true" version="5" changeset="56512917" timestamp="2018-02-20T08:02:34Z" user="SHCat" uid="4641415" lat="23.0013821" lon="120.2154993"/>
 <node id="3479452632" visible="true" version="7" changeset="57282747" timestamp="2018-03-18T06:33:23Z" user="SHCat" uid="4641415" lat="22.9949786" lon="120.2180669"/>
 <node id="3562634141" visible="true" version="1" changeset="31624866" timestamp="2015-06-01T05:16:50Z" user="Kagami" uid="189328" lat="22.9744939" lon="120.2411494"/>
 <node id="3562634143" visible="true" version="1" changeset="31624866" timestamp="2015-06-01T05:16:50Z" user="Kagami" uid="189328" lat="22.9745965" lon="120.2411643"/>
 <node id="3562634145" visible="true" version="1" changeset="31624866" timestamp="2015-06-01T05:16:50Z" user="Kagami" uid="189328" lat="22.9755560" lon="120.2412316"/>
 <node id="3562634147" visible="true" version="1" changeset="31624866" timestamp="2015-06-01T05:16:50Z" user="Kagami" uid="189328" lat="22.9756625" lon="120.2412578"/>
 <node id="3562634153" visible="true" version="1" changeset="31624866" timestamp="2015-06-01T05:16:50Z" user="Kagami" uid="189328" lat="22.9762328" lon="120.2414145"/>
 <node id="3562634156" visible="true" version="1" changeset="31624866" timestamp="2015-06-01T05:16:50Z" user="Kagami" uid="189328" lat="22.9764045" lon="120.2414257"/>
 <node id="3562634167" visible="true" version="2" changeset="44623999" timestamp="2016-12-23T15:04:16Z" user="Kagami" uid="189328" lat="22.9776549" lon="120.2414738"/>
 <node id="3562634168" visible="true" version="2" changeset="44623999" timestamp="2016-12-23T15:04:16Z" user="Kagami" uid="189328" lat="22.9779910" lon="120.2415411"/>
 <node id="3562634170" visible="true" version="1" changeset="31624866" timestamp="2015-06-01T05:16:51Z" user="Kagami" uid="189328" lat="22.9784106" lon="120.2416197"/>
 <node id="3562634172" visible="true" version="2" changeset="44623999" timestamp="2016-12-23T15:04:16Z" user="Kagami" uid="189328" lat="22.9790951" lon="120.2417669"/>
 <node id="4052205742" visible="true" version="7" changeset="57282747" timestamp="2018-03-18T06:33:23Z" user="SHCat" uid="4641415" lat="22.9950945" lon="120.2180759"/>
 <node id="4117809984" visible="true" version="8" changeset="57282747" timestamp="2018-03-18T06:33:23Z" user="SHCat" uid="4641415" lat="22.9934228" lon="120.2179463"/>
 <node id="4335085706" visible="true" version="6" changeset="56663456" timestamp="2018-02-25T15:19:12Z" user="SHCat" uid="4641415" lat="22.9854152" lon="120.2258047"/>
 <node id="4335085799" visible="true" version="4" changeset="56663456" timestamp="2018-02-25T15:19:12Z" user="SHCat" uid="4641415" lat="22.9850679" lon="120.2249114"/>
 <node id="4408384525" visible="true" version="6" changeset="51772102" timestamp="2017-09-06T07:43:47Z" user="SHCat" uid="4641415" lat="22.9921949" lon="120.2199657"/>
 <node id="4568883277" visible="true" version="1" changeset="44623999" timestamp="2016-12-23T15:04:14Z" user="Kagami" uid="189328" lat="22.9749137" lon="120.2412415">
  <tag k="bus" v="yes"/>
  <tag k="highway" v="bus_stop"/>
  <tag k="name" v="仁德轉運站"/>
  <tag k="network" v="臺南市公車"/>
  <tag k="operator" v="臺南市公車"/>
  <tag k="public_transport" v="platform"/>
 </node>
 <node id="4568883279" visible="true" version="1" changeset="44623999" timestamp="2016-12-23T15:04:14Z" user="Kagami" uid="189328" lat="22.9770226" lon="120.2414936">
  <tag k="bus" v="yes"/>
  <tag k="highway" v="bus_stop"/>
  <tag k="name" v="嘉南療養院(裕忠路)"/>
  <tag k="network" v="臺南市公車"/>
  <tag k="operator" v="臺南市公車"/>
  <tag k="public_transport" v="platform"/>
 </node>
 <node id="4957072760" visible="true" version="2" changeset="57282747" timestamp="2018-03-18T06:33:23Z" user="SHCat" uid="4641415" lat="22.9996136" lon="120.2184373"/>
 <node id="4966464499" visible="true" version="1" changeset="50235794" timestamp="2017-07-12T17:05:15Z" user="SHCat" uid="4641415" lat="22.9798579" lon="120.2420694"/>
 <node id="4966464500" visible="true" version="1" changeset="50235794" timestamp="2017-07-12T17:05:15Z" user="SHCat" uid="4641415" lat="22.9798749" lon="120.2444866"/>
 <node id="4966464501" visible="true" version="1" changeset="50235794" timestamp="2017-07-12T17:05:15Z" user="SHCat" uid="4641415" lat="22.9798730" lon="120.2442470"/>
 <node id="4966464513" visible="true" version="1" changeset="50235794" timestamp="2017-07-12T17:05:15Z" user="SHCat" uid="4641415" lat="22.9863134" lon="120.2396233"/>
 <node id="4966466024" visible="true" version="1" changeset="50235794" timestamp="2017-07-12T17:05:16Z" user="SHCat" uid="4641415" lat="22.9867853" lon="120.2396291"/>
 <node id="5325339188" visible="true" version="2" changeset="56567816" timestamp="2018-02-22T03:52:13Z" user="SHCat" uid="4641415" lat="22.9913360" lon="120.2237954"/>
 <node id="5361756105" visible="true" version="2" changeset="56512917" timestamp="2018-02-20T08:02:34Z" user="SHCat" uid="4641415" lat="23.0011963" lon="120.2170991"/>
 <node id="5424067642" visible="true" version="1" changeset="56512917" timestamp="2018-02-20T08:02:29Z" user="SHCat" uid="4641415" lat="23.0012905" lon="120.2161622"/>
 <node id="5424067649" visible="true" version="2" changeset="57282747" timestamp="2018-03-18T06:33:23Z" user="SHCat" uid="4641415" lat="23.0008046" lon="120.2185336">
  <tag k="highway" v="crossing"/>
 </node>
 <node id="5424675409" visible="true" version="1" changeset="56522849" timestamp="2018-02-20T14:46:29Z" user="SHCat" uid="4641415" lat="23.0015451" lon="120.2130340">
  <tag k="highway" v="crossing"/>
 </node>
 <node id="5424675706" visible="true" version="1" changeset="56522849" timestamp="2018-02-20T14:46:31Z" user="SHCat" uid="4641415" lat="23.0010590" lon="120.2184502">
  <tag k="highway" v="crossing"/>
 </node>
 <node id="5424675711" visible="true" version="1" changeset="56522849" timestamp="2018-02-20T14:46:31Z" user="SHCat" uid="4641415" lat="23.0012203" lon="120.2168602">
  <tag k="highway" v="crossing"/>
 </node>
 <node id="5424675714" visible="true" version="1" changeset="56522849" timestamp="2018-02-20T14:46:31Z" user="SHCat" uid="4641415" lat="23.0011905" lon="120.2171562">
  <tag k="highway" v="crossing"/>
 </node>
 <node id="5424675721" visible="true" version="1" changeset="56522849" timestamp="2018-02-20T14:46:32Z" user="SHCat" uid="4641415" lat="23.0014900" lon="120.2147851">
  <tag k="highway" v="crossing"/>
 </node>
 <node id="5424732018" visible="true" version="1" changeset="56523599" timestamp="2018-02-20T15:17:21Z" user="SHCat" uid="4641415" lat="22.9854478" lon="120.2225885">
  <tag k="highway" v="crossing"/>
 </node>
 <node id="5424733937" visible="true" version="1" changeset="56523599" timestamp="2018-02-20T15:17:21Z" user="SHCat" uid="4641415" lat="22.9914199" lon="120.2235250"/>
 <node id="5424733946" visible="true" version="1" changeset="56523599" timestamp="2018-02-20T15:17:22Z" user="SHCat" uid="4641415" lat="22.9855992" lon="120.2225769">
  <tag k="highway" v="crossing"/>
 </node>
 <node id="5424733953" visible="true" version="1" changeset="56523599" timestamp="2018-02-20T15:17:22Z" user="SHCat" uid="4641415" lat="22.9870795" lon="120.2230552"/>
 <node id="5424733957" visible="true" version="1" changeset="56523599" timestamp="2018-02-20T15:17:22Z" user="SHCat" uid="4641415" lat="22.9877382" lon="120.2233040"/>
 <node id="5424733961" visible="true" version="1" changeset="56523599" timestamp="2018-02-20T15:17:22Z" user="SHCat" uid="4641415" lat="22.9881902" lon="120.2234754"/>
 <node id="5424733966" visible="true" version="1" changeset="56523599" timestamp="2018-02-20T15:17:22Z" user="SHCat" uid="4641415" lat="22.9890955" lon="120.2238188"/>
 <node id="5424733972" visible="true" version="1" changeset="56523599" timestamp="2018-02-20T15:17:22Z" user="SHCat" uid="4641415" lat="22.9912313" lon="120.2241346"/>
 <node id="5424733974" visible="true" version="1" changeset="56523599" timestamp="2018-02-20T15:17:22Z" user="SHCat" uid="4641415" lat="22.9909787" lon="120.2245350">
  <tag k="highway" v="crossing"/>
 </node>
 <node id="5424817186" visible="true" version="1" changeset="56524745" timestamp="2018-02-20T16:01:37Z" user="SHCat" uid="4641415" lat="23.0000873" lon="120.2127622">
  <tag k="highway" v="crossing"/>
 </node>
 <node id="5485764939" visible="true" version="1" changeset="57282747" timestamp="2018-03-18T06:33:17Z" user="SHCat" uid="4641415" lat="22.9961452" lon="120.2181573"/>
 <node id="5485764943" visible="true" version="1" changeset="57282747" timestamp="2018-03-18T06:33:17Z" user="SHCat" uid="4641415" lat="22.9963841" lon="120.2181763"/>
 <way id="38755026" visible="true" version="22" changeset="48893083" timestamp="2017-05-22T16:16:36Z" user="Supaplex" uid="274857">
  <nd ref="335913528"/>
  <nd ref="296967567"/>
  <nd ref="1721697109"/>
  <tag k="highway" v="tertiary"/>
  <tag k="name" v="東寧路"/>
  <tag k="name:en" v="Dongning Road"/>
  <tag k="name:zh" v="東寧路"/>
 </way>
 <way id="108071649" visible="true" version="2" changeset="16760105" timestamp="2013-06-30T03:46:38Z" user="Kagami" uid="189328">
  <nd ref="1240617783"/>
  <nd ref="1240618154"/>
  <nd ref="1240618649"/>
  <tag k="highway" v="secondary"/>
  <tag k="name" v="小東路"/>
  <tag k="oneway" v="yes"/>
  <tag k="ref" v="180"/>
 </way>
 <way id="108071698" visible="true" version="6" changeset="48893083" timestamp="2017-05-22T16:17:01Z" user="Supaplex" uid="274857">
  <nd ref="1240618461"/>
  <nd ref="1240617783"/>
  <tag k="highway" v="secondary"/>
  <tag k="layer" v="-1"/>
  <tag k="motorcycle" v="no"/>
  <tag k="motorroad" v="yes"/>
  <tag k="name" v="小東路"/>
  <tag k="name:en" v="Xiaodong Road"/>
  <tag k="name:zh" v="小東路"/>
  <tag k="oneway" v="yes"/>
  <tag k="ref" v="180"/>
 </way>
 <way id="228022792" visible="true" version="9" changeset="50316683" timestamp="2017-07-16T02:25:38Z" user="SHCat" uid="4641415">
  <nd ref="864831599"/>
  <nd ref="2833144824"/>
  <nd ref="1268711606"/>
  <nd ref="2833118044"/>
  <nd ref="2144927860"/>
  <nd ref="2144927867"/>
  <nd ref="1240618188"/>
  <tag k="highway" v="primary"/>
  <tag k="layer" v="2"/>
  <tag k="name" v="北門路二段"/>
  <tag k="name:en" v="Beimen Road Sec. 2"/>
  <tag k="name:zh" v="北門路二段"/>
  <tag k="oneway" v="no"/>
  <tag k="ref" v="20"/>
  <tag k="ref:en" v="Provincial Highway 20"/>
  <tag k="ref:zh" v="台20線"/>
 </way>
 <way id="228022801" visible="true" version="4" changeset="56512917" timestamp="2018-02-20T08:02:39Z" user="SHCat" uid="4641415">
  <nd ref="256016226"/>
  <nd ref="1240618278"/>
  <tag k="highway" v="residential"/>
  <tag k="name" v="勝利路"/>
 </way>
 <way id="253751064" visible="true" version="11" changeset="51772102" timestamp="2017-09-06T07:43:49Z" user="SHCat" uid="4641415">
  <nd ref="1650294487"/>
  <nd ref="3019036790"/>
  <nd ref="2833118029"/>
  <nd ref="2467264692"/>
  <nd ref="4408384525"/>
  <nd ref="3076706423"/>
  <nd ref="2833129211"/>
  <nd ref="1723131492"/>
  <nd ref="256016221"/>
  <tag k="highway" v="tertiary"/>
  <tag k="name" v="東寧路"/>
  <tag k="name:en" v="Dongning Road"/>
  <tag k="name:zh" v="東寧路"/>
  <tag k="ref" v="22"/>
 </way>
 <way id="298592946" visible="true" version="3" changeset="51772102" timestamp="2017-09-06T07:43:49Z" user="SHCat" uid="4641415">
  <nd ref="1240618440"/>
  <nd ref="1240618163"/>
  <tag k="highway" v="tertiary"/>
  <tag k="name" v="東寧路"/>
  <tag k="name:en" v="Dongning Road"/>
  <tag k="name:zh" v="東寧路"/>
  <tag k="ref" v="22"/>
 </way>
 <way id="298592948" visible="true" version="10" changeset="57282747" timestamp="2018-03-18T06:33:27Z" user="SHCat" uid="4641415">
  <nd ref="256016221"/>
  <nd ref="4117809984"/>
  <nd ref="3479452632"/>
  <nd ref="4052205742"/>
  <nd ref="1268711590"/>
  <nd ref="1723635528"/>
  <nd ref="1723635535"/>
  <nd ref="1723635546"/>
  <nd ref="1723635551"/>
  <nd ref="5485764939"/>
  <nd ref="355961064"/>
  <tag k="highway" v="residential"/>
  <tag k="name" v="勝利路"/>
  <tag k="name:en" v="Shengli Road"/>
  <tag k="name:zh" v="勝利路"/>
  <tag k="oneway" v="no"/>
  <tag k="surface" v="asphalt"/>
 </way>
 <way id="298597679" visible="true" version="6" changeset="56523599" timestamp="2018-02-20T15:17:32Z" user="SHCat" uid="4641415">
  <nd ref="1240618141"/>
  <nd ref="5424732018"/>
  <nd ref="1721697102"/>
  <nd ref="1721697101"/>
  <nd ref="1727568978"/>
  <nd ref="1240618302"/>
  <tag k="highway" v="secondary"/>
  <tag k="name" v="東門路二段"/>
  <tag k="name:en" v="Dongmen Road Sec. 2"/>
  <tag k="name:zh" v="東門路二段"/>
  <tag k="ref" v="182"/>
 </way>
 <way id="298597681" visible="true" version="10" changeset="57198215" timestamp="2018-03-15T04:50:55Z" user="s88239" uid="5406836">
  <nd ref="1240618141"/>
  <nd ref="5424733946"/>
  <nd ref="1727569026"/>
  <nd ref="5424733953"/>
  <nd ref="1650311040"/>
  <nd ref="5424733957"/>
  <nd ref="1650311059"/>
  <nd ref="5424733961"/>
  <nd ref="1723635440"/>
  <nd ref="5424733966"/>
  <nd ref="1723131428"/>
  <nd ref="5424733974"/>
  <nd ref="1240618440"/>
  <tag k="highway" v="tertiary"/>
  <tag k="name" v="林森路二段"/>
  <tag k="name:en" v="Linsen Road Section 2"/>
  <tag k="name:zh" v="林森路二段"/>
  <tag k="oneway" v="yes"/>
  <tag k="ref" v="27"/>
 </way>
 <way id="298597683" visible="true" version="3" changeset="49018811" timestamp="2017-05-27T08:09:21Z" user="Supaplex" uid="274857">
  <nd ref="2469869715"/>
  <nd ref="2469869745"/>
  <nd ref="2469869754"/>
  <nd ref="3024869186"/>
  <nd ref="2469869835"/>
  <nd ref="2469869860"/>
  <tag k="highway" v="unclassified"/>
  <tag k="name" v="裕信路"/>
  <tag k="oneway" v="yes"/>
 </way>
 <way id="298597689" visible="true" version="1" changeset="24836872" timestamp="2014-08-18T15:59:33Z" user="Kagami" uid="189328">
  <nd ref="1725808539"/>
  <nd ref="1725808538"/>
  <nd ref="1725808540"/>
  <nd ref="2205385002"/>
  <nd ref="1725808562"/>
  <tag k="highway" v="residential"/>
  <tag k="name" v="裕平路"/>
  <tag k="oneway" v="yes"/>
 </way>
 <way id="298597692" visible="true" version="1" changeset="24836872" timestamp="2014-08-18T15:59:33Z" user="Kagami" uid="189328">
  <nd ref="1725808418"/>
  <nd ref="1725808448"/>
  <nd ref="2469869909"/>
  <nd ref="2469869929"/>
  <nd ref="1725808505"/>
  <nd ref="1725808539"/>
  <tag k="highway" v="residential"/>
  <tag k="name" v="裕忠路"/>
  <tag k="oneway" v="yes"/>
 </way>
 <way id="298597694" visible="true" version="3" changeset="50235794" timestamp="2017-07-12T17:05:26Z" user="SHCat" uid="4641415">
  <nd ref="1725808303"/>
  <nd ref="2469869717"/>
  <nd ref="4966464499"/>
  <nd ref="2469869719"/>
  <nd ref="2469869721"/>
  <nd ref="2469869722"/>
  <nd ref="1725808301"/>
  <nd ref="4966464501"/>
  <nd ref="1725808300"/>
  <nd ref="4966464500"/>
  <nd ref="1725808298"/>
  <tag k="highway" v="residential"/>
  <tag k="name" v="裕敬路"/>
 </way>
 <way id="298597695" visible="true" version="1" changeset="24836872" timestamp="2014-08-18T15:59:33Z" user="Kagami" uid="189328">
  <nd ref="1725808298"/>
  <nd ref="2469869715"/>
  <tag k="highway" v="residential"/>
  <tag k="name" v="裕敬路"/>
 </way>
 <way id="298597700" visible="true" version="7" changeset="50235794" timestamp="2017-07-12T17:05:28Z" user="SHCat" uid="4641415">
  <nd ref="1725808562"/>
  <nd ref="1725808608"/>
  <nd ref="4966464513"/>
  <nd ref="1725808648"/>
  <nd ref="4966466024"/>
  <nd ref="2205385043"/>
  <tag k="highway" v="service"/>
  <tag k="name" v="裕農三街"/>
 </way>
 <way id="298597702" visible="true" version="9" changeset="51772102" timestamp="2017-09-06T07:43:48Z" user="SHCat" uid="4641415">
  <nd ref="3070820668"/>
  <nd ref="2794611790"/>
  <nd ref="1725808772"/>
  <nd ref="1725808770"/>
  <nd ref="3232607263"/>
  <nd ref="2205385078"/>
  <nd ref="2239492102"/>
  <nd ref="2204802349"/>
  <nd ref="3232727827"/>
  <nd ref="3232727826"/>
  <nd ref="2204802343"/>
  <nd ref="335913528"/>
  <tag k="highway" v="tertiary"/>
  <tag k="name" v="裕農路"/>
  <tag k="name:en" v="Yunong Road"/>
  <tag k="name:zh" v="裕農路"/>
  <tag k="ref" v="22"/>
 </way>
 <way id="307096543" visible="true" version="7" changeset="57282747" timestamp="2018-03-18T06:33:27Z" user="SHCat" uid="4641415">
  <nd ref="355961064"/>
  <nd ref="5485764943"/>
  <nd ref="2578269068"/>
  <nd ref="2578269075"/>
  <nd ref="4957072760"/>
  <nd ref="5424067649"/>
  <nd ref="256016226"/>
  <tag k="highway" v="residential"/>
  <tag k="name" v="勝利路"/>
  <tag k="name:en" v="Shengli Road"/>
  <tag k="name:zh" v="勝利路"/>
  <tag k="oneway" v="no"/>
  <tag k="surface" v="asphalt"/>
 </way>
 <way id="313194339" visible="true" version="2" changeset="48921730" timestamp="2017-05-23T16:24:07Z" user="Supaplex" uid="274857">
  <nd ref="1240618031"/>
  <nd ref="1240618649"/>
  <tag k="highway" v="primary"/>
  <tag k="layer" v="2"/>
  <tag k="name" v="北門路"/>
  <tag k="name:en" v="Beimen Road"/>
  <tag k="name:zh" v="北門路"/>
  <tag k="oneway" v="no"/>
  <tag k="ref" v="20"/>
  <tag k="ref:en" v="Provincial Highway 20"/>
  <tag k="ref:zh" v="台20線"/>
 </way>
 <way id="313194390" visible="true" version="7" changeset="56522849" timestamp="2018-02-20T14:46:48Z" user="SHCat" uid="4641415">
  <nd ref="1240618278"/>
  <nd ref="5424675706"/>
  <nd ref="5424675714"/>
  <nd ref="5361756105"/>
  <nd ref="5424675711"/>
  <nd ref="5424067642"/>
  <nd ref="3256639839"/>
  <nd ref="5424675721"/>
  <nd ref="1240618340"/>
  <nd ref="1240617667"/>
  <tag k="highway" v="secondary"/>
  <tag k="name" v="小東路"/>
  <tag k="name:en" v="Xiaodong Road"/>
  <tag k="name:zh" v="小東路"/>
  <tag k="oneway" v="yes"/>
  <tag k="ref" v="180"/>
 </way>
 <way id="315702598" visible="true" version="6" changeset="56524745" timestamp="2018-02-20T16:01:44Z" user="SHCat" uid="4641415">
  <nd ref="1240618188"/>
  <nd ref="1268711613"/>
  <nd ref="5424817186"/>
  <nd ref="5424675409"/>
  <nd ref="1240618031"/>
  <tag k="highway" v="primary"/>
  <tag k="layer" v="2"/>
  <tag k="name" v="北門路二段"/>
  <tag k="name:en" v="Beimen Road Sec. 2"/>
  <tag k="name:zh" v="北門路二段"/>
  <tag k="oneway" v="no"/>
  <tag k="ref" v="20"/>
  <tag k="ref:en" v="Provincial Highway 20"/>
  <tag k="ref:zh" v="台20線"/>
 </way>
 <way id="350501716" visible="true" version="3" changeset="44623999" timestamp="2016-12-23T15:04:18Z" user="Kagami" uid="189328">
  <nd ref="3562634141"/>
  <nd ref="3562634143"/>
  <nd ref="3562634145"/>
  <nd ref="3562634147"/>
  <nd ref="3562634153"/>
  <nd ref="3562634156"/>
  <nd ref="3562634167"/>
  <nd ref="3562634168"/>
  <nd ref="3562634170"/>
  <nd ref="3562634172"/>
  <nd ref="1725808263"/>
  <tag k="highway" v="residential"/>
  <tag k="name" v="裕忠路"/>
  <tag k="oneway" v="yes"/>
 </way>
 <way id="392464671" visible="true" version="3" changeset="49607434" timestamp="2017-06-17T06:10:07Z" user="Supaplex" uid="274857">
  <nd ref="1721697109"/>
  <nd ref="1721697108"/>
  <tag k="highway" v="tertiary"/>
  <tag k="name" v="東寧路"/>
  <tag k="name:en" v="Dongning Road"/>
  <tag k="name:zh" v="東寧路"/>
 </way>
 <way id="405115644" visible="true" version="6" changeset="56523599" timestamp="2018-02-20T15:17:33Z" user="SHCat" uid="4641415">
  <nd ref="1240618163"/>
  <nd ref="5424733972"/>
  <nd ref="5325339188"/>
  <nd ref="1723635450"/>
  <nd ref="5424733937"/>
  <nd ref="1723635452"/>
  <nd ref="1723131486"/>
  <nd ref="256016208"/>
  <tag k="highway" v="tertiary"/>
  <tag k="name" v="東寧路"/>
  <tag k="name:en" v="Dongning Road"/>
  <tag k="name:zh" v="東寧路"/>
  <tag k="ref" v="22"/>
 </way>
 <way id="405115645" visible="true" version="4" changeset="51772102" timestamp="2017-09-06T07:43:49Z" user="SHCat" uid="4641415">
  <nd ref="256016208"/>
  <nd ref="1650294487"/>
  <tag k="highway" v="tertiary"/>
  <tag k="name" v="東寧路"/>
  <tag k="name:en" v="Dongning Road"/>
  <tag k="name:zh" v="東寧路"/>
  <tag k="ref" v="22"/>
 </way>
 <way id="461383348" visible="true" version="1" changeset="44623999" timestamp="2016-12-23T15:04:15Z" user="Kagami" uid="189328">
  <nd ref="1725808263"/>
  <nd ref="1725808303"/>
  <tag k="highway" v="residential"/>
  <tag k="name" v="裕忠路"/>
  <tag k="oneway" v="yes"/>
 </way>
 <way id="496177978" visible="true" version="2" changeset="49153939" timestamp="2017-06-01T05:47:48Z" user="happychang" uid="5644877">
  <nd ref="2205385043"/>
  <nd ref="1725808713"/>
  <nd ref="2205385055"/>
  <nd ref="1725808751"/>
  <nd ref="3070820668"/>
  <tag k="highway" v="service"/>
  <tag k="name" v="裕農三街"/>
 </way>
 <way id="496257372" visible="true" version="1" changeset="49017271" timestamp="2017-05-27T06:09:05Z" user="SHCat" uid="4641415">
  <nd ref="1240617667"/>
  <nd ref="1240618461"/>
  <tag k="highway" v="secondary"/>
  <tag k="name" v="小東路"/>
  <tag k="name:en" v="Xiaodong Road"/>
  <tag k="name:zh" v="小東路"/>
  <tag k="oneway" v="yes"/>
  <tag k="ref" v="180"/>
 </way>
 <way id="496261719" visible="true" version="2" changeset="56663456" timestamp="2018-02-25T15:19:12Z" user="SHCat" uid="4641415">
  <nd ref="1240618302"/>
  <nd ref="1727568976"/>
  <nd ref="4335085799"/>
  <nd ref="4335085706"/>
  <nd ref="1650311027"/>
  <nd ref="1240618561"/>
  <nd ref="2205385018"/>
  <nd ref="1727569033"/>
  <nd ref="1240618115"/>
  <nd ref="1723131384"/>
  <nd ref="1723131385"/>
  <nd ref="2204802270"/>
  <nd ref="1728838658"/>
  <nd ref="1728838681"/>
  <nd ref="1721697108"/>
  <tag k="highway" v="tertiary"/>
  <tag k="name" v="裕農路"/>
  <tag k="name:en" v="Yunong Road"/>
  <tag k="name:zh" v="裕農路"/>
 </way>
 <way id="496332180" visible="true" version="1" changeset="49028461" timestamp="2017-05-27T16:24:19Z" user="SHCat" uid="4641415">
  <nd ref="1725808398"/>
  <nd ref="1725808418"/>
  <tag k="highway" v="residential"/>
  <tag k="name" v="裕文路"/>
 </way>
 <way id="496714506" visible="true" version="1" changeset="49077766" timestamp="2017-05-29T15:58:28Z" user="Kagami" uid="189328">
  <nd ref="1725808411"/>
  <nd ref="1725808398"/>
  <tag k="highway" v="residential"/>
  <tag k="name" v="裕文路"/>
 </way>
 <way id="496714507" visible="true" version="1" changeset="49077766" timestamp="2017-05-29T15:58:28Z" user="Kagami" uid="189328">
  <nd ref="2469869860"/>
  <nd ref="1725808411"/>
  <tag k="highway" v="residential"/>
  <tag k="name" v="裕文路"/>
 </way>
 <relation id="4064419" visible="true" version="20" changeset="56663456" timestamp="2018-02-25T15:19:14Z" user="SHCat" uid="4641415">
  <member type="node" ref="4568883277" role="platform"/>
  <member type="node" ref="4568883279" role="platform"/>
  <member type="node" ref="3024869204" role="platform"/>
  <member type="node" ref="3024869198" role="platform"/>
  <member type="node" ref="3024869202" role="platform"/>
  <member type="node" ref="3024869209" role="platform"/>
  <member type="node" ref="3024869207" role="platform"/>
  <member type="node" ref="2794611845" role="platform"/>
  <member type="node" ref="2794611833" role="platform"/>
  <member type="node" ref="2794611836" role="platform"/>
  <member type="node" ref="2794611872" role="platform"/>
  <member type="node" ref="2794611809" role="platform"/>
  <member type="node" ref="2794611897" role="platform"/>
  <member type="node" ref="2794611893" role="platform"/>
  <member type="node" ref="2794611858" role="platform"/>
  <member type="node" ref="2794611829" role="platform"/>
  <member type="node" ref="3024807439" role="platform"/>
  <member type="node" ref="2592689579" role="platform"/>
  <member type="node" ref="2592689573" role="platform"/>
  <member type="node" ref="2592689575" role="platform"/>
  <member type="node" ref="2592689570" role="platform"/>
  <member type="node" ref="2163590091" role="platform"/>
  <member type="node" ref="2163590085" role="platform"/>
  <member type="node" ref="2163590079" role="platform"/>
  <member type="way" ref="350501716" role=""/>
  <member type="way" ref="461383348" role=""/>
  <member type="way" ref="298597694" role=""/>
  <member type="way" ref="298597695" role=""/>
  <member type="way" ref="298597683" role=""/>
  <member type="way" ref="496714507" role=""/>
  <member type="way" ref="496714506" role=""/>
  <member type="way" ref="496332180" role=""/>
  <member type="way" ref="298597692" role=""/>
  <member type="way" ref="298597689" role=""/>
  <member type="way" ref="298597700" role=""/>
  <member type="way" ref="496177978" role=""/>
  <member type="way" ref="298597702" role=""/>
  <member type="way" ref="38755026" role=""/>
  <member type="way" ref="392464671" role=""/>
  <member type="way" ref="496261719" role=""/>
  <member type="way" ref="298597679" role=""/>
  <member type="way" ref="298597681" role=""/>
  <member type="way" ref="298592946" role=""/>
  <member type="way" ref="405115644" role=""/>
  <member type="way" ref="405115645" role=""/>
  <member type="way" ref="253751064" role=""/>
  <member type="way" ref="298592948" role=""/>
  <member type="way" ref="307096543" role=""/>
  <member type="way" ref="228022801" role=""/>
  <member type="way" ref="313194390" role=""/>
  <member type="way" ref="496257372" role=""/>
  <member type="way" ref="108071698" role=""/>
  <member type="way" ref="108071649" role=""/>
  <member type="way" ref="313194339" role=""/>
  <member type="way" ref="315702598" role=""/>
  <member type="way" ref="228022792" role=""/>
  <tag k="from" v="裕聖里"/>
  <tag k="name" v="6路(往裕聖里_返程)"/>
  <tag k="public_transport:version" v="2"/>
  <tag k="ref" v="6"/>
  <tag k="route" v="bus"/>
  <tag k="to" v="火車北站"/>
  <tag k="type" v="route"/>
 </relation>
</osm>
