{
  "Info": [
    {
      "IsSuccess": "True",
      "InAddress": "臺南市善化區陽光三街168號",
      "InSRS": "EPSG:4326",
      "InFuzzyType": "[單雙號機制]+[最近門牌號機制]",
      "InFuzzyBuffer": "0",
      "InIsOnlyFullMatch": "False",
      "InIsSupportPast": "True",
      "InIsShowCodeBase": "True",
      "InIsLockCounty": "True",
      "InIsLockTown": "False",
      "InIsLockVillage": "False",
      "InIsLockRoadSection": "False",
      "InIsLockLane": "False",
      "InIsLockAlley": "False",
      "InIsLockArea": "False",
      "InIsSameNumber_SubNumber": "True",
      "InCanIgnoreVillage": "True",
      "InCanIgnoreNeighborhood": "True",
      "InReturnMaxCount": "0",
      "OutTotal": "1",
      "OutMatchType": "模糊比對",
      "OutMatchCode": "[臺南市]\tT:1,V:-1,R:2,S:-1,L:-1,A:-1,SA:-1,T:-1,AR:-1,NO:1,E:-1,N:-1",
      "OutTraceInfo": "[臺南市]\t { 模糊比對 } (善化區)\t找到符合的[鄉鎮市區]，(陽光三街)\t找不到符合的[路街名]，進行轉換搜尋[街變成路，路變成街]，轉換搜尋找到符合的[路街名]，(168號)\t找到符合的[門牌號碼]，模糊比對找到 1 筆符合的門牌地址。"
    }
  ],
  "AddressList": [
    {
      "PERIOD": "",
      "FULL_ADDR": "臺南市善化區蓮潭里11鄰陽光三路168號",
      "COUNTY": "臺南市",
      "TOWN": "善化區",
      "VILLAGE": "蓮潭里",
      "NEIGHBORHOOD": "11鄰",
      "ROAD": "陽光三路",
      "SECTION": "",
      "LANE": "",
      "ALLEY": "",
      "SUB_ALLEY": "",
      "TONG": "",
      "AREA": "",
      "NUMBER": "168號",
      "X": 120.309910,
      "Y": 23.114730,
      "CODEBASE": "A6719-0293-00",
      "CODE1": "A6719-15-010",
      "CODE2": "A6719-15"
    }
  ]
}